fastgam/__init__.py
fastgam/additive.py
fastgam/fast.py
fastgam-1.0.2.dist-info/METADATA
fastgam-1.0.2.dist-info/WHEEL
fastgam-1.0.2.dist-info/licenses/LICENSE
fastgam-1.0.2.dist-info/RECORD
