Metadata-Version: 2.4
Name: fastgam
Version: 1.0.2
Summary: A package implementing fast generalized additive models
Project-URL: Homepage, https://github.com/NathanDoumeche/fastgam
Project-URL: Issues, https://github.com/NathanDoumeche/fastgam/issues
Author-email: Nathan Doumèche <nathan.doumeche@gmail.com>, Francis Bach <francis.bach@inria.fr>, Claire Boyer <claire.boyer@universite-paris-saclay.fr>, Gérard Biau <gerard.biau@sorbonne-universite.fr>
License-Expression: MIT
License-File: LICENSE
Classifier: Operating System :: OS Independent
Classifier: Programming Language :: Python :: 3
Requires-Python: >=3.9
Requires-Dist: finufft
Requires-Dist: numpy>=2.0.0
